{"title":"TODAY LIFE","slug":"today life","date":"2021-09-13T17:05:26.000Z","updated":"2021-09-13T17:05:26.850Z","comments":true,"path":"api/articles/today life.json","photos":[],"link":"","excerpt":null,"covers":null,"content":"<h2 id=\"Towseo’s-today-life\"><a href=\"#Towseo’s-today-life\" class=\"headerlink\" title=\"Towseo’s today life\"></a>Towseo’s today life</h2><blockquote>\n<p>A great weekday！</p>\n</blockquote>\n<center><font face=\"微软雅黑\" color=\"red\" size=\"20\">HAPPY</font></center>\n","categories":[],"tags":[]}